get_stick_bugged_lol_fork-1.0.2.dist-info/licenses/LICENSE
gsbl/__init__.py
gsbl/__main__.py
gsbl/stick_bug.py
gsbl/media/note0.wav
gsbl/media/note1.wav
gsbl/media/note2.wav
gsbl/media/note3.wav
gsbl/media/note4.wav
gsbl/media/note5.wav
gsbl/media/note6.wav
gsbl/media/note7.wav
gsbl/media/note8.wav
gsbl/media/note9.wav
gsbl/media/stick_bug.mp4
gsbl/media/transform.wav
get_stick_bugged_lol_fork-1.0.2.dist-info/METADATA
get_stick_bugged_lol_fork-1.0.2.dist-info/WHEEL
get_stick_bugged_lol_fork-1.0.2.dist-info/entry_points.txt
get_stick_bugged_lol_fork-1.0.2.dist-info/top_level.txt
get_stick_bugged_lol_fork-1.0.2.dist-info/RECORD
