Metadata-Version: 2.4
Name: get-stick-bugged-lol-fork
Version: 1.0.2
Summary: 'Get stick bugged' video generator
Home-page: https://github.com/yesseruser/get_stick_bugged_lol
Author: yesseruser
Classifier: Programming Language :: Python :: 3
Classifier: License :: OSI Approved :: MIT License
Classifier: Operating System :: OS Independent
Requires-Python: >=3.6
License-File: LICENSE
Requires-Dist: pylsd-nova>=1.2.0
Requires-Dist: numpy
Requires-Dist: Pillow
Requires-Dist: moviepy
Dynamic: author
Dynamic: classifier
Dynamic: description
Dynamic: description-content-type
Dynamic: home-page
Dynamic: license-file
Dynamic: requires-dist
Dynamic: requires-python
Dynamic: summary
